CMakeLists.txt
LICENSE.txt
MANIFEST.in
README.rst
setup.py
include/grakopp/ast-io.hpp
include/grakopp/ast.hpp
include/grakopp/buffer.hpp
include/grakopp/exceptions.hpp
include/grakopp/grakopp.hpp
include/grakopp/parser.hpp
python/grakopp/__init__.py
python/grakopp/ast-io.pxd
python/grakopp/ast.cpp
python/grakopp/ast.pxd
python/grakopp/ast.pyx
python/grakopp/buffer.cpp
python/grakopp/buffer.pxd
python/grakopp/buffer.pyx
python/grakopp/exceptions.py
python/grakopp/parser.pxd
python/grakopp/tool.py
python/grakopp.egg-info/PKG-INFO
python/grakopp.egg-info/SOURCES.txt
python/grakopp.egg-info/dependency_links.txt
python/grakopp.egg-info/entry_points.txt
python/grakopp.egg-info/not-zip-safe
python/grakopp.egg-info/top_level.txt
python/grakopp/codegen/__init__.py
python/grakopp/codegen/cpp.py
python/grakopp/codegen/hpp.py
python/grakopp/codegen/pxd.py
python/grakopp/codegen/pyx.py
tests/CMakeLists.txt
tests/basic/CMakeLists.txt
tests/basic/basic-001-disjunction.in
tests/basic/basic-001-disjunction.out
tests/basic/basic-002-sequence.in
tests/basic/basic-002-sequence.out
tests/basic/basic-003-group.in
tests/basic/basic-003-group.out
tests/basic/basic-004-optional.in
tests/basic/basic-004-optional.out
tests/basic/basic-005-optional.in
tests/basic/basic-005-optional.out
tests/basic/basic-006-closure.in
tests/basic/basic-006-closure.out
tests/basic/basic-007-closure.in
tests/basic/basic-007-closure.out
tests/basic/basic-008-closure.in
tests/basic/basic-008-closure.out
tests/basic/basic-009-positive_closure.in
tests/basic/basic-009-positive_closure.out
tests/basic/basic-010-positive_closure.in
tests/basic/basic-010-positive_closure.out
tests/basic/basic-011-positive_closure.in
tests/basic/basic-011-positive_closure.out
tests/basic/basic.peg
tools/CMakeLists.txt
tools/astcmp.cpp
tools/astify.cpp