Metadata-Version: 1.1
Name: grakopp
Version: 0.1.0
Summary: Grako++ is a packrat parser runtime for Grako, written in C++.
Home-page: https://github.com/lambdafu/grakopp
Author: Marcus Brinkmann
Author-email: m.brinkmann@semantics.de
License: BSD
Keywords: grako parser peg
Platform: UNKNOWN
Classifier: Development Status :: 3 - Alpha
Classifier: Environment :: Console
Classifier: Intended Audience :: Developers
Classifier: Intended Audience :: Science/Research
Classifier: License :: OSI Approved :: BSD License
Classifier: Operating System :: OS Independent
Classifier: Natural Language :: English
Classifier: Operating System :: OS Independent
Classifier: Programming Language :: C++
Classifier: Programming Language :: Python :: 2.7
Classifier: Programming Language :: Python :: 3.4
Classifier: Topic :: Software Development :: Code Generators
Classifier: Topic :: Software Development :: Compilers
Classifier: Topic :: Software Development :: Interpreters
Classifier: Topic :: Text Processing :: General
Requires: grako
Requires: cython
